rhoa/__init__.py
rhoa/data.py
rhoa/indicators.py
rhoa/preprocess.py
rhoa/targets.py
rhoa-0.1.6.dist-info/licenses/LICENSE
rhoa-0.1.6.dist-info/METADATA
rhoa-0.1.6.dist-info/WHEEL
rhoa-0.1.6.dist-info/top_level.txt
rhoa-0.1.6.dist-info/RECORD
